fundamentals/__init__.py
fundamentals/__version__.py
fundamentals/cl_utils.py
fundamentals/daemonise.py
fundamentals/docstring_test.py
fundamentals/fmultiprocess.py
fundamentals/logs.py
fundamentals/times.py
fundamentals/tools.py
fundamentals/utKit.py
fundamentals/commonutils/__init__.py
fundamentals/commonutils/getpackagepath.py
fundamentals/download/__init__.py
fundamentals/download/_dump_files_to_local_drive.py
fundamentals/download/_fetch.py
fundamentals/download/append_now_datestamp_to_filename.py
fundamentals/download/extract_filename_from_url.py
fundamentals/download/get_now_datetime_filestamp.py
fundamentals/download/multiobject_download.py
fundamentals/download/tests/__init__.py
fundamentals/download/tests/test__dump_files_to_local_drive.py
fundamentals/download/tests/test__fetch.py
fundamentals/download/tests/test_append_now_datestamp_to_filename.py
fundamentals/download/tests/test_extract_filename_from_url.py
fundamentals/download/tests/test_get_now_datetime_filestamp.py
fundamentals/download/tests/test_multiobject_download.py
fundamentals/files/__init__.py
fundamentals/files/fileChunker.py
fundamentals/files/list_of_dictionaries_to_mysql_inserts.py
fundamentals/files/recursive_directory_listing.py
fundamentals/files/tag.py
fundamentals/files/tests/test_fileChunker.py
fundamentals/files/tests/test_list_of_dictionaries_to_mysql_inserts.py
fundamentals/files/tests/test_recursive_directory_listing.py
fundamentals/files/tests/test_tag.py
fundamentals/files/tests/__pycache__/test_fileChunker.cpython-38-pytest-7.1.2.pyc
fundamentals/files/tests/__pycache__/test_list_of_dictionaries_to_mysql_inserts.cpython-38-pytest-7.1.2.pyc
fundamentals/files/tests/__pycache__/test_recursive_directory_listing.cpython-38-pytest-7.1.2.pyc
fundamentals/files/tests/__pycache__/test_tag.cpython-38-pytest-7.1.2.pyc
fundamentals/mysql/__init__.py
fundamentals/mysql/convert_dictionary_to_mysql_table.py
fundamentals/mysql/database.py
fundamentals/mysql/directory_script_runner.py
fundamentals-2.7.8.dist-info/LICENSE
fundamentals-2.7.8.dist-info/METADATA
fundamentals-2.7.8.dist-info/WHEEL
fundamentals-2.7.8.dist-info/entry_points.txt
fundamentals-2.7.8.dist-info/top_level.txt
fundamentals-2.7.8.dist-info/RECORD
