Metadata-Version: 2.1
Name: fundamentals
Version: 2.7.8
Summary: Some fundamental tools required by most self-respecting python-packages bundled in one place. Very opinionated project setup tools including logging, plain-text settings files and database connections.
Home-page: https://github.com/thespacedoctor/fundamentals
Download-URL: https://github.com/thespacedoctor/fundamentals/archive/v2.7.8.zip
Author: David Young
Author-email: davidrobertyoung@gmail.com
License: MIT
Keywords: logging, database
Classifier: Development Status :: 4 - Beta
Classifier: License :: OSI Approved :: MIT License
Classifier: Programming Language :: Python :: 3.9
Classifier: Topic :: Utilities
License-File: LICENSE
Requires-Dist: pyyaml
Requires-Dist: fundamentals
Requires-Dist: future
Requires-Dist: docopt
Requires-Dist: psutil
Requires-Dist: python-dateutil
Requires-Dist: requests
Requires-Dist: python-daemon
Requires-Dist: tqdm
